odoo/addons/mrp_production_quant_manual_assign/README.rst
odoo/addons/mrp_production_quant_manual_assign/__init__.py
odoo/addons/mrp_production_quant_manual_assign/__manifest__.py
odoo/addons/mrp_production_quant_manual_assign/i18n/es.po
odoo/addons/mrp_production_quant_manual_assign/i18n/fr.po
odoo/addons/mrp_production_quant_manual_assign/i18n/it.po
odoo/addons/mrp_production_quant_manual_assign/i18n/mrp_production_quant_manual_assign.pot
odoo/addons/mrp_production_quant_manual_assign/i18n/pt_BR.po
odoo/addons/mrp_production_quant_manual_assign/models/__init__.py
odoo/addons/mrp_production_quant_manual_assign/models/stock_move.py
odoo/addons/mrp_production_quant_manual_assign/readme/CONTRIBUTORS.rst
odoo/addons/mrp_production_quant_manual_assign/readme/DESCRIPTION.rst
odoo/addons/mrp_production_quant_manual_assign/readme/USAGE.rst
odoo/addons/mrp_production_quant_manual_assign/static/description/icon.png
odoo/addons/mrp_production_quant_manual_assign/static/description/index.html
odoo/addons/mrp_production_quant_manual_assign/views/mrp_production_views.xml
odoo/addons/mrp_production_quant_manual_assign/wizards/__init__.py
odoo/addons/mrp_production_quant_manual_assign/wizards/assign_manual_quants.py
odoo/addons/mrp_production_quant_manual_assign/wizards/assign_manual_quants_view.xml
odoo14_addon_mrp_production_quant_manual_assign-14.0.1.0.1.dev12.dist-info/METADATA
odoo14_addon_mrp_production_quant_manual_assign-14.0.1.0.1.dev12.dist-info/WHEEL
odoo14_addon_mrp_production_quant_manual_assign-14.0.1.0.1.dev12.dist-info/top_level.txt
odoo14_addon_mrp_production_quant_manual_assign-14.0.1.0.1.dev12.dist-info/RECORD
