Metadata-Version: 2.1
Name: odoo14-addon-mrp_production_quant_manual_assign
Version: 14.0.1.0.1.dev12
Summary: Production - Manual Quant Assignment
Home-page: https://github.com/OCA/manufacture
Author: Quartile Limited, ForgeFlow, Odoo Community Association (OCA)
Author-email: support@odoo-community.org
License: AGPL-3
Classifier: Programming Language :: Python
Classifier: Framework :: Odoo
Classifier: Framework :: Odoo :: 14.0
Classifier: License :: OSI Approved :: GNU Affero General Public License v3
Requires-Python: >=3.6
Requires-Dist: odoo14-addon-stock-quant-manual-assign
Requires-Dist: odoo <14.1dev,>=14.0a
